relion/__init__.py
relion/parse_project.py
relion/_parser/__init__.py
relion/_parser/autopick.py
relion/_parser/class2D.py
relion/_parser/class3D.py
relion/_parser/combine_star_files.py
relion/_parser/combine_star_job.py
relion/_parser/cryolo.py
relion/_parser/ctffind.py
relion/_parser/initialmodel.py
relion/_parser/jobtype.py
relion/_parser/motioncorrection.py
relion/_parser/processgraph.py
relion/_parser/processnode.py
relion/_parser/relativeicethickness.py
relion/_parser/relion_pipeline.py
relion/_parser/select.py
relion/cli/__init__.py
relion/cli/current_job.py
relion/cli/pipeline_viewer.py
relion/cli/print_default_options.py
relion/cli/project_linker.py
relion/cli/refine_pipeline.py
relion/cli/run_pipeline.py
relion/cryolo_relion_it/__init__.py
relion/cryolo_relion_it/cryolo_external_job.py
relion/cryolo_relion_it/cryolo_fine_tune_job.py
relion/cryolo_relion_it/cryolo_relion_it.py
relion/cryolo_relion_it/dls_options.py
relion/cryolo_relion_it/fsc_fitting_external_job.py
relion/cryolo_relion_it/icebreaker_histogram.py
relion/cryolo_relion_it/mask_soft_edge_external_job.py
relion/cryolo_relion_it/reconstruct_halves_external_job.py
relion/cryolo_relion_it/select_and_split_external_job.py
relion/dbmodel/__init__.py
relion/dbmodel/dbgraph.py
relion/dbmodel/dbnode.py
relion/dbmodel/modeltables.py
relion/node/__init__.py
relion/node/environment.py
relion/node/graph.py
relion/pipeline/__init__.py
relion/pipeline/extra_options.py
relion/pipeline/options.py
relion/pipeline/refine.py
relion/zocalo/__init__.py
relion/zocalo/alchemy.py
relion/zocalo/class2d_wrapper.py
relion/zocalo/class3d_wrapper.py
relion/zocalo/cluster_submission.py
relion/zocalo/cryolo.py
relion/zocalo/ctffind.py
relion/zocalo/denoise.py
relion/zocalo/extract.py
relion/zocalo/icebreaker.py
relion/zocalo/images.py
relion/zocalo/images_service_plugin.py
relion/zocalo/ispyb_buffer.py
relion/zocalo/ispyb_recipe_tools.py
relion/zocalo/ispyb_service.py
relion/zocalo/motioncorr.py
relion-0.13.16.dist-info/LICENSE
relion-0.13.16.dist-info/METADATA
relion-0.13.16.dist-info/WHEEL
relion-0.13.16.dist-info/entry_points.txt
relion-0.13.16.dist-info/top_level.txt
relion-0.13.16.dist-info/RECORD
