Metadata-Version: 2.1
Name: relion
Version: 0.13.16
Summary: Relion Python API
Author: Diamond Light Source - Scientific Software et al.
Author-email: scientificsoftware@diamond.ac.uk
License: GPLv2
Project-URL: Documentation, https://python-relion.readthedocs.io/
Project-URL: GitHub, https://github.com/DiamondLightSource/python-relion
Project-URL: Bug-Tracker, https://github.com/DiamondLightSource/python-relion/issues
Keywords: relion
Classifier: Development Status :: 3 - Alpha
Classifier: Intended Audience :: Developers
Classifier: License :: OSI Approved :: GNU General Public License v2 (GPLv2)
Classifier: Natural Language :: English
Classifier: Programming Language :: Python :: 3
Classifier: Programming Language :: Python :: 3.8
Classifier: Programming Language :: Python :: 3.9
Classifier: Programming Language :: Python :: 3.10
Requires-Python: >=3.8
License-File: LICENSE
Requires-Dist: gemmi
Requires-Dist: htcondor
Requires-Dist: importlib-metadata
Requires-Dist: ispyb
Requires-Dist: marshmallow-sqlalchemy
Requires-Dist: matplotlib
Requires-Dist: mrcfile
Requires-Dist: numpy
Requires-Dist: opencv-python-headless
Requires-Dist: pandas
Requires-Dist: pillow
Requires-Dist: plotly
Requires-Dist: pydantic ==1.10.7
Requires-Dist: pyyaml
Requires-Dist: starfile
Requires-Dist: workflows
Requires-Dist: zocalo
